kelpsong/__init__.py
kelpsong/release_info.py
kelpsong-0.1.0.dist-info/LICENSE
kelpsong-0.1.0.dist-info/METADATA
kelpsong-0.1.0.dist-info/WHEEL
kelpsong-0.1.0.dist-info/top_level.txt
kelpsong-0.1.0.dist-info/RECORD
